{
  "generatedAt": "2026-05-08T21:54:17.808Z",
  "usingExampleData": true,
  "sourceFiles": {
    "areas": "data\\raw\\areas.csv",
    "trends": "data\\raw\\trends.example.csv"
  },
  "rawAreaRowCount": 2879,
  "areaCount": 2783,
  "duplicatePostcodeDistrictCount": 95,
  "trendPointCount": 7,
  "statusCounts": {
    "AT_RISK": 1027,
    "VULNERABLE": 1097,
    "PROTECTED": 659
  },
  "coverageBands": {
    "atRisk": "coverage < 90",
    "vulnerable": "90 <= coverage < 95",
    "protected": "coverage >= 95"
  }
}
